<?xml version="1.0" encoding="UTF-8"?>
<!DOCTYPE mapper PUBLIC "-//mybatis.org//DTD Mapper 3.0//EN"
        "http://mybatis.org/dtd/mybatis-3-mapper.dtd">
<mapper namespace="com.ffs.server.mapper.TargetingRuleMapper">

    <resultMap id="ruleMap" type="com.ffs.server.model.entity.TargetingRule">
        <id property="id" column="id"/>
        <result property="flagId" column="flag_id"/>
        <result property="priority" column="priority"/>
        <result property="attribute" column="attribute"/>
        <result property="operator" column="operator"/>
        <result property="value" column="`value`"/>
        <result property="serveValue" column="serve_value"/>
        <result property="enabled" column="enabled"/>
        <result property="createdAt" column="created_at"/>
    </resultMap>

    <select id="findByFlagIdOrderByPriority" resultMap="ruleMap">
        SELECT * FROM targeting_rule WHERE flag_id = #{flagId} AND enabled = TRUE ORDER BY priority ASC
    </select>

    <select id="findById" resultMap="ruleMap">
        SELECT * FROM targeting_rule WHERE id = #{id}
    </select>

    <insert id="insert" useGeneratedKeys="true" keyProperty="id">
        INSERT INTO targeting_rule (flag_id, priority, attribute, operator, `value`, serve_value, enabled, created_at)
        VALUES (#{flagId}, #{priority}, #{attribute}, #{operator}, #{value}, #{serveValue}, #{enabled}, NOW())
    </insert>

    <update id="update">
        UPDATE targeting_rule SET
            priority = #{priority},
            attribute = #{attribute},
            operator = #{operator},
            `value` = #{value},
            serve_value = #{serveValue},
            enabled = #{enabled}
        WHERE id = #{id}
    </update>

    <delete id="deleteById">
        DELETE FROM targeting_rule WHERE id = #{id}
    </delete>

    <update id="deactivateByFlagId">
        UPDATE targeting_rule SET enabled = FALSE WHERE flag_id = #{flagId}
    </update>
</mapper>
